bmds/__init__.py
bmds/constants.py
bmds/exceptions.py
bmds/plotting.py
bmds/session.py
bmds/settings.py
bmds/utils.py
bmds/version.py
bmds/benchmarks/__init__.py
bmds/benchmarks/analyses.py
bmds/benchmarks/config.py
bmds/benchmarks/datasets.py
bmds/benchmarks/db.py
bmds/benchmarks/models.py
bmds/benchmarks/run.py
bmds/benchmarks/executors/__init__.py
bmds/benchmarks/executors/model_fit.py
bmds/benchmarks/executors/shared.py
bmds/bin/BMDS270/Acknowledgement.txt
bmds/bin/BMDS270/DichoHill.exe
bmds/bin/BMDS270/cancer.exe
bmds/bin/BMDS270/exponential.exe
bmds/bin/BMDS270/gamma.exe
bmds/bin/BMDS270/hill.exe
bmds/bin/BMDS270/libgcc_s_dw2-1.dll
bmds/bin/BMDS270/libgfortran-3.dll
bmds/bin/BMDS270/libquadmath-0.dll
bmds/bin/BMDS270/log_probit_bg_dose.exe
bmds/bin/BMDS270/logist.exe
bmds/bin/BMDS270/ms_combo.exe
bmds/bin/BMDS270/multistage.exe
bmds/bin/BMDS270/poly.exe
bmds/bin/BMDS270/power.exe
bmds/bin/BMDS270/probit.exe
bmds/bin/BMDS270/weibull.exe
bmds/bin/BMDS330/libDRBMD.dll
bmds/bin/BMDS330/libDRBMD.dylib
bmds/bin/BMDS330/libDRBMD.so
bmds/bmds2/__init__.py
bmds/bmds2/batch.py
bmds/bmds2/exports.py
bmds/bmds2/parser.py
bmds/bmds2/reporter.py
bmds/bmds2/sessions.py
bmds/bmds2/logic/__init__.py
bmds/bmds2/logic/recommender.py
bmds/bmds2/logic/rules.py
bmds/bmds2/models/__init__.py
bmds/bmds2/models/base.py
bmds/bmds2/models/continuous.py
bmds/bmds2/models/dichotomous.py
bmds/bmds3/__init__.py
bmds/bmds3/batch.py
bmds/bmds3/constants.py
bmds/bmds3/reporting.py
bmds/bmds3/selected.py
bmds/bmds3/sessions.py
bmds/bmds3/models/__init__.py
bmds/bmds3/models/base.py
bmds/bmds3/models/continuous.py
bmds/bmds3/models/dichotomous.py
bmds/bmds3/models/ma.py
bmds/bmds3/recommender/__init__.py
bmds/bmds3/recommender/checks.py
bmds/bmds3/recommender/constants.py
bmds/bmds3/recommender/default.json
bmds/bmds3/recommender/recommender.py
bmds/bmds3/types/__init__.py
bmds/bmds3/types/common.py
bmds/bmds3/types/continuous.py
bmds/bmds3/types/dichotomous.py
bmds/bmds3/types/ma.py
bmds-25.1.dist-info/LICENSE
bmds-25.1.dist-info/METADATA
bmds-25.1.dist-info/WHEEL
bmds-25.1.dist-info/entry_points.txt
bmds-25.1.dist-info/top_level.txt
bmds-25.1.dist-info/RECORD
