Metadata-Version: 2.2
Name: bmds
Version: 25.1
Summary: A Python interface for the USEPA Benchmark dose modeling software (BMDS)
Author: Andy Shapiro
Author-email: shapiromatron@gmail.com
License: MIT
Project-URL: Documentation, https://bmds.readthedocs.io/
Project-URL: Changes, https://github.com/shapiromatron/bmds/blob/main/docs/docs/history.md
Project-URL: Code, https://github.com/shapiromatron/bmds
Project-URL: Issue Tracker, https://github.com/shapiromatron/bmds/issues
Project-URL: Download, https://pypi.org/project/bmds/
Classifier: Intended Audience :: Science/Research
Classifier: License :: OSI Approved :: MIT License
Classifier: Natural Language :: English
Classifier: Programming Language :: Python :: 3.11
Classifier: Topic :: Scientific/Engineering
License-File: LICENSE
Requires-Dist: matplotlib
Requires-Dist: numpy
Requires-Dist: openpyxl
Requires-Dist: pandas
Requires-Dist: pydantic>2
Requires-Dist: python-docx
Requires-Dist: scipy
Requires-Dist: simple-settings
Requires-Dist: tabulate
Requires-Dist: tqdm
Provides-Extra: benchmarks
Requires-Dist: SQLAlchemy<2,>1.4; extra == "benchmarks"
